setup.py
modelstatus/__init__.py
modelstatus/api.py
modelstatus/exceptions.py
modelstatus/utils.py
modelstatus/tests/test_external.py
modelstatus/tests/test_utils.py
modelstatus_client.egg-info/PKG-INFO
modelstatus_client.egg-info/SOURCES.txt
modelstatus_client.egg-info/dependency_links.txt
modelstatus_client.egg-info/requires.txt
modelstatus_client.egg-info/top_level.txt