Metadata-Version: 1.1
Name: modelstatus-client
Version: 2.0.0
Summary: Modelstatus REST API client
Home-page: https://github.com/metno/python-modelstatus-client
Author: MET Norway
Author-email: UNKNOWN
License: UNKNOWN
Download-URL: https://github.com/metno/python-modelstatus-client
Platform: UNKNOWN
